pandasai_langchain/__init__.py
pandasai_langchain/langchain.py
pandasai_langchain-0.1.5.dist-info/METADATA
pandasai_langchain-0.1.5.dist-info/WHEEL
pandasai_langchain-0.1.5.dist-info/RECORD
